gdmec23120239/__init__.py
gdmec23120239-0.1.0.dist-info/METADATA
gdmec23120239-0.1.0.dist-info/WHEEL
gdmec23120239-0.1.0.dist-info/entry_points.txt
gdmec23120239-0.1.0.dist-info/RECORD
